numpy/__config__.py
numpy/__init__.py
numpy/__init__.pyi.py
numpy/_core.py
numpy/_distributor_init.py
numpy/_globals.py
numpy/_pyinstaller.py
numpy/_pytesttester.py
numpy/_typing.py
numpy/array_api.py
numpy/compat.py
numpy/ctypeslib.py
numpy/doc.py
numpy/dtypes.py
numpy/exceptions.py
numpy/f2py.py
numpy/fft.py
numpy/linalg.py
numpy/ma.py
numpy/matlib.py
numpy/matlib.py.py
numpy/polynomial.py
numpy/py.typed
numpy/random.py
numpy/testing.py
numpy/tests.py
numpy/typing.py
numpy/version.py
numpy/_utils/__init__.py
numpy/_utils/_convertions.py
numpy/_utils/_inspect.py
numpy/_utils/_pep440.py
numpy/core/__init__.py
numpy/core/_add_newdocs.py
numpy/core/_add_newdocs_scalars.py
numpy/core/_asarray.py
numpy/core/_dtype.py
numpy/core/_dtype_ctypes.py
numpy/core/_exceptions.py
numpy/core/_internal.py
numpy/core/_machar.py
numpy/core/_methods.py
numpy/core/_multiarray_tests.cpython-312-x86_64-linux-gnu.so
numpy/core/_multiarray_umath.cpython-312-x86_64-linux-gnu.so
numpy/core/_string_helpers.py
numpy/core/_type_aliases.py
numpy/core/_ufunc_config.py
numpy/core/arrayprint.py
numpy/core/cversions.py
numpy/core/defchararray.py
numpy/core/einsumfunc.py
numpy/core/fromnumeric.py
numpy/core/function_base.py
numpy/core/getlimits.py
numpy/core/include.py
numpy/core/lib.py
numpy/core/memmap.py
numpy/core/multiarray.py
numpy/core/numeric.py
numpy/core/numerictypes.py
numpy/core/overrides.py
numpy/core/records.py
numpy/core/shape_base.py
numpy/core/umath.py
numpy/core/umath_tests.py
numpy/lib/__init__.py
numpy/lib/_datasource.py
numpy/lib/_iotools.py
numpy/lib/_version.py
numpy/lib/arraypad.py
numpy/lib/arraysetops.py
numpy/lib/arrayterator.py
numpy/lib/format.py
numpy/lib/function_base.py
numpy/lib/histograms.py
numpy/lib/index_tricks.py
numpy/lib/mixins.py
numpy/lib/nanfunctions.py
numpy/lib/npyio.py
numpy/lib/polynomial.py
numpy/lib/scimath.py
numpy/lib/setup.py
numpy/lib/shape_base.py
numpy/lib/stride_tricks.py
numpy/lib/twodim_base.py
numpy/lib/type_check.py
numpy/lib/ufunclike.py
numpy_lite-1.26.4.dist-info/METADATA
numpy_lite-1.26.4.dist-info/WHEEL
numpy_lite-1.26.4.dist-info/top_level.txt
numpy_lite-1.26.4.dist-info/RECORD
