Metadata-Version: 2.4
Name: numpy-lite
Version: 1.26.4
Summary: Ultra-light minimal NumPy build (core functionality only) for AWS Lambda / serverless.
Home-page: https://github.com/JacquieAM/numpy-lite
Author: JacquieAM
Classifier: Programming Language :: Python :: 3.12
Classifier: Operating System :: OS Independent
Requires-Python: >=3.12
Dynamic: author
Dynamic: classifier
Dynamic: description
Dynamic: description-content-type
Dynamic: home-page
Dynamic: requires-python
Dynamic: summary
